frules/__init__.py
frules/_test.py
frules/adverbs.py
frules/errors.py
frules/expressions.py
frules/norms.py
frules/primitives.py
frules/rules.py
frules-0.2.0.dist-info/LICENSE
frules-0.2.0.dist-info/METADATA
frules-0.2.0.dist-info/WHEEL
frules-0.2.0.dist-info/top_level.txt
frules-0.2.0.dist-info/RECORD
