Metadata-Version: 2.1
Name: frules
Version: 0.2.0
Summary: simple functional fuzzy rules implementation
Home-page: https://github.com/swistakm/frules
Author: Michał Jaworski
Author-email: swistakm@gmail.com
License: UNKNOWN
Platform: UNKNOWN
Classifier: Development Status :: 4 - Beta
Classifier: Intended Audience :: Developers
Classifier: License :: OSI Approved :: BSD License
Classifier: Operating System :: OS Independent
Classifier: Programming Language :: Python
Classifier: Programming Language :: Python :: 3
